pandas_estat/__init__.py
pandas_estat/appid.py
pandas_estat/base.py
pandas_estat/exceptions.py
pandas_estat/statsdata.py
pandas_estat/statslist.py
pandas_estat-0.3.4.dist-info/LICENSE
pandas_estat-0.3.4.dist-info/WHEEL
pandas_estat-0.3.4.dist-info/METADATA
pandas_estat-0.3.4.dist-info/RECORD
