Metadata-Version: 2.1
Name: pandas-estat
Version: 0.3.4
Summary: Fetch e-Stat data as Pandas DataFrame.
Home-page: https://github.com/simaki/pandas-estat
License: BSD-3-Clause
Author: Shota Imaki
Author-email: shota.imaki.0801@gmail.com
Requires-Python: >=3.7.12,<4.0.0
Classifier: License :: OSI Approved :: BSD License
Classifier: Programming Language :: Python :: 3
Classifier: Programming Language :: Python :: 3.8
Classifier: Programming Language :: Python :: 3.9
Classifier: Programming Language :: Python :: 3.10
Classifier: Programming Language :: Python :: 3.11
Requires-Dist: pandas (>=1.3.3,<2.0.0)
Requires-Dist: requests (>=2.26.0,<3.0.0)
Project-URL: Repository, https://github.com/simaki/pandas-estat
